{"id":"bw10-69","tcgplayer":{"holofoil":[{"d":"2025-09-14","market":1.34,"low":0.39,"mid":1.32,"high":8.63,"directLow":null},{"d":"2025-09-15","market":1.34,"low":0.39,"mid":1.32,"high":8.63,"directLow":null}],"reverseHolofoil":[{"d":"2025-09-14","market":1.41,"low":0.63,"mid":1,"high":5.94,"directLow":null},{"d":"2025-09-15","market":1.41,"low":0.63,"mid":1,"high":5.94,"directLow":null}]},"cardmarket":{"holofoil":[{"d":"2025-09-14","trend":1.96,"avg7":2.11,"avg30":1.82,"low":0.25,"salesWeek":null},{"d":"2025-09-15","trend":1.96,"avg7":2.11,"avg30":1.82,"low":0.25,"salesWeek":null}],"reverseHolofoil":[{"d":"2025-09-14","trend":2.77,"avg7":2.11,"avg30":1.82,"low":0.25,"salesWeek":null},{"d":"2025-09-15","trend":2.77,"avg7":2.11,"avg30":1.82,"low":0.25,"salesWeek":null}]},"pricecharting":{}}