{"id":"bw7-142","tcgplayer":{"holofoil":[{"d":"2025-09-14","market":157.49,"low":78,"mid":200,"high":201,"directLow":null},{"d":"2025-09-15","market":157.49,"low":78,"mid":200,"high":201,"directLow":null},{"d":"2025-09-16","market":157.49,"low":78,"mid":200,"high":201,"directLow":null},{"d":"2025-09-17","market":157.49,"low":78,"mid":200,"high":201,"directLow":null}]},"cardmarket":{"holofoil":[{"d":"2025-09-14","trend":40.22,"avg7":32.41,"avg30":29.68,"low":4.99,"salesWeek":null},{"d":"2025-09-15","trend":40.22,"avg7":32.41,"avg30":29.68,"low":4.99,"salesWeek":null},{"d":"2025-09-16","trend":37.24,"avg7":29.67,"avg30":29.68,"low":4.99,"salesWeek":null},{"d":"2025-09-17","trend":37.73,"avg7":32.53,"avg30":29.68,"low":4.99,"salesWeek":null}],"reverseHolofoil":[{"d":"2025-09-14","trend":27.43,"avg7":32.41,"avg30":29.68,"low":4.99,"salesWeek":null},{"d":"2025-09-15","trend":27.43,"avg7":32.41,"avg30":29.68,"low":4.99,"salesWeek":null},{"d":"2025-09-16","trend":27.43,"avg7":29.67,"avg30":29.68,"low":4.99,"salesWeek":null},{"d":"2025-09-17","trend":27.43,"avg7":32.53,"avg30":29.68,"low":4.99,"salesWeek":null}]},"pricecharting":{}}