{"id":"ecard2-66","tcgplayer":{"normal":[{"d":"2025-09-14","market":45.79,"low":69.99,"mid":71.95,"high":129.99,"directLow":null},{"d":"2025-09-15","market":45.79,"low":69.99,"mid":71.95,"high":129.99,"directLow":null},{"d":"2025-09-16","market":45.79,"low":69.99,"mid":71.95,"high":129.99,"directLow":null}],"reverseHolofoil":[{"d":"2025-09-14","market":62.3,"low":111.11,"mid":122.22,"high":149.99,"directLow":null},{"d":"2025-09-15","market":62.3,"low":111.11,"mid":122.22,"high":149.99,"directLow":null},{"d":"2025-09-16","market":62.3,"low":111.11,"mid":122.22,"high":149.99,"directLow":null}]},"cardmarket":{"normal":[{"d":"2025-09-14","trend":15.55,"avg7":14.27,"avg30":10.1,"low":1.5,"salesWeek":null},{"d":"2025-09-15","trend":15.55,"avg7":14.27,"avg30":10.1,"low":1.5,"salesWeek":null},{"d":"2025-09-16","trend":15.55,"avg7":14.27,"avg30":10.1,"low":1.5,"salesWeek":null}],"reverseHolofoil":[{"d":"2025-09-14","trend":14.37,"avg7":14.27,"avg30":10.1,"low":1.5,"salesWeek":null},{"d":"2025-09-15","trend":14.37,"avg7":14.27,"avg30":10.1,"low":1.5,"salesWeek":null},{"d":"2025-09-16","trend":13.81,"avg7":14.27,"avg30":10.1,"low":1.5,"salesWeek":null}]},"pricecharting":{}}